geonode_importer-1.1.3.dist-info/licenses/LICENSE
importer/__init__.py
importer/apps.py
importer/celery_app.py
importer/celery_tasks.py
importer/datastore.py
importer/db_router.py
importer/models.py
importer/orchestrator.py
importer/publisher.py
importer/settings.py
importer/urls.py
importer/utils.py
importer/views.py
importer/api/__init__.py
importer/api/exception.py
importer/api/serializer.py
importer/api/tests.py
importer/api/urls.py
importer/api/views.py
importer/handlers/__init__.py
importer/handlers/apps.py
importer/handlers/base.py
importer/handlers/tests.py
importer/handlers/utils.py
importer/handlers/common/__init__.py
importer/handlers/common/metadata.py
importer/handlers/common/raster.py
importer/handlers/common/remote.py
importer/handlers/common/serializer.py
importer/handlers/common/test_remote.py
importer/handlers/common/tests_raster.py
importer/handlers/common/tests_vector.py
importer/handlers/common/vector.py
importer/handlers/csv/__init__.py
importer/handlers/csv/exceptions.py
importer/handlers/csv/handler.py
importer/handlers/csv/tests.py
importer/handlers/geojson/__init__.py
importer/handlers/geojson/exceptions.py
importer/handlers/geojson/handler.py
importer/handlers/geojson/tests.py
importer/handlers/geotiff/__init__.py
importer/handlers/geotiff/exceptions.py
importer/handlers/geotiff/handler.py
importer/handlers/geotiff/tests.py
importer/handlers/gpkg/__init__.py
importer/handlers/gpkg/exceptions.py
importer/handlers/gpkg/handler.py
importer/handlers/gpkg/tasks.py
importer/handlers/gpkg/tests.py
importer/handlers/kml/__init__.py
importer/handlers/kml/exceptions.py
importer/handlers/kml/handler.py
importer/handlers/kml/tests.py
importer/handlers/remote/__init__.py
importer/handlers/remote/tiles3d.py
importer/handlers/remote/wms.py
importer/handlers/remote/serializers/__init__.py
importer/handlers/remote/serializers/wms.py
importer/handlers/remote/tests/__init__.py
importer/handlers/remote/tests/test_3dtiles.py
importer/handlers/remote/tests/test_wms.py
importer/handlers/shapefile/__init__.py
geonode_importer-1.1.3.dist-info/METADATA
geonode_importer-1.1.3.dist-info/WHEEL
geonode_importer-1.1.3.dist-info/top_level.txt
geonode_importer-1.1.3.dist-info/RECORD
