Metadata-Version: 2.4
Name: geonode-importer
Version: 1.1.3
Home-page: https://github.com/GeoNode/geonode-importer
Author: geosolutions-it
Author-email: info@geosolutionsgroup.com
Project-URL: Bug Tracker, https://github.com/geosolutions-it/geonode-importer/issues
Platform: any
Classifier: Environment :: Web Environment
Classifier: Framework :: Django :: 3.2
Classifier: Framework :: Django :: 4.2
Classifier: Programming Language :: Python
Classifier: Programming Language :: Python :: 3.8
Classifier: Programming Language :: Python :: 3.9
Classifier: Programming Language :: Python :: 3.10
License-File: LICENSE
Requires-Dist: setuptools>=59
Requires-Dist: gdal<=3.4.3
Requires-Dist: pdok-geopackage-validator==0.8.5
Requires-Dist: geonode-django-dynamic-model==0.4.0
Dynamic: author
Dynamic: author-email
Dynamic: classifier
Dynamic: description
Dynamic: description-content-type
Dynamic: home-page
Dynamic: license-file
Dynamic: platform
Dynamic: requires-dist
